README.md
setup.cfg
setup.py
el_compX_scraper.egg-info/PKG-INFO
el_compX_scraper.egg-info/SOURCES.txt
el_compX_scraper.egg-info/dependency_links.txt
el_compX_scraper.egg-info/requires.txt
el_compX_scraper.egg-info/top_level.txt
scraper/OQMD_new_version.py
scraper/__init__.py
scraper/data_structure.py
scraper/example.py
scraper/generic_scraper.py
scraper/periodic_table_new.py
test/test_OQMD_scraper.py
test/test_periodic_table_scraper.py