Metadata-Version: 2.1
Name: el-compX-scraper
Version: 0.1.5
Summary: This package scrapes features of elements and compounds from specified websites
Home-page: https://github.com/barmiy01/Webscraping_Project.git
Author: Bilal Armiyawo
License: MIT
Platform: UNKNOWN
